{
  "appInfo" : {
    "build" : "211.7628.21",
    "buildDate" : "2021-06-30T12:04:59.14Z[UTC]",
    "productCode" : "IC",
    "generated" : "2021-09-16T01:19:22.9878194Z",
    "os" : "Windows 10 10.0",
    "runtime" : "JetBrains s.r.o. 11.0.11 11.0.11+9-b1341.60"
  },
  "runtimeInfo" : {
    "maxMemory" : 536870912,
    "numberOfProcessors" : 8,
    "maxNumberOfIndexingThreads" : 4,
    "maxSizeOfFileForIntelliSense" : 2560000,
    "maxSizeOfFileForContentLoading" : 20971520
  },
  "projectIndexingHistory" : {
    "projectName" : "intellij-sdk-code-samples-main",
    "times" : {
      "totalUpdatingTime" : 6606943900,
      "indexingTime" : 0,
      "contentLoadingTime" : 0,
      "scanFilesTime" : 6486519400,
      "pushPropertiesTime" : 97101600,
      "indexExtensionsTime" : 0,
      "updatingStart" : "2021-09-16T01:19:16.3795022Z",
      "updatingEnd" : "2021-09-16T01:19:22.9778144Z",
      "totalSuspendedTime" : 0,
      "wasInterrupted" : false
    },
    "fileCount" : {
      "numberOfFileProviders" : 8,
      "numberOfScannedFiles" : 50103,
      "numberOfFilesIndexedByInfrastructureExtensionsDuringScan" : 0,
      "numberOfFilesScheduledForIndexingAfterScan" : 0,
      "numberOfFilesIndexedByInfrastructureExtensionsDuringIndexingStage" : 0,
      "numberOfFilesIndexedWithLoadingContent" : 0
    },
    "totalStatsPerFileType" : [ ],
    "totalStatsPerIndexer" : [ ],
    "scanningStatistics" : [ {
      "providerName" : "JDK 16",
      "numberOfScannedFiles" : 40717,
      "numberOfSkippedFiles" : 0,
      "numberOfFilesForIndexing" : 0,
      "numberOfFilesFullyIndexedByInfrastructureExtensions" : 0,
      "scanningTime" : 4169377300,
      "timeProcessingUpToDateFiles" : 443838300,
      "timeUpdatingContentLessIndexes" : 153931900,
      "timeIndexingWithoutContent" : 0
    }, {
      "providerName" : "Module 'intellij-sdk-code-samples-main'",
      "numberOfScannedFiles" : 9164,
      "numberOfSkippedFiles" : 0,
      "numberOfFilesForIndexing" : 0,
      "numberOfFilesFullyIndexedByInfrastructureExtensions" : 0,
      "scanningTime" : 2287645000,
      "timeProcessingUpToDateFiles" : 124855100,
      "timeUpdatingContentLessIndexes" : 47790000,
      "timeIndexingWithoutContent" : 0
    }, {
      "providerName" : "com.intellij.javaee.ExternalResourcesRootsProvider@7cce72bf",
      "numberOfScannedFiles" : 221,
      "numberOfSkippedFiles" : 4,
      "numberOfFilesForIndexing" : 0,
      "numberOfFilesFullyIndexedByInfrastructureExtensions" : 0,
      "scanningTime" : 1040291300,
      "timeProcessingUpToDateFiles" : 54837100,
      "timeUpdatingContentLessIndexes" : 5666900,
      "timeIndexingWithoutContent" : 0
    }, {
      "providerName" : "com.intellij.ide.scratch.ScratchesAndConsolesIndexSetContributor@7f1c12bd",
      "numberOfScannedFiles" : 1,
      "numberOfSkippedFiles" : 0,
      "numberOfFilesForIndexing" : 0,
      "numberOfFilesFullyIndexedByInfrastructureExtensions" : 0,
      "scanningTime" : 438017300,
      "timeProcessingUpToDateFiles" : 235300,
      "timeUpdatingContentLessIndexes" : 58300,
      "timeIndexingWithoutContent" : 0
    }, {
      "providerName" : "org.jetbrains.kotlin.idea.core.script.dependencies.KotlinScriptDependenciesIndexableSetContributor@3c5780d6",
      "numberOfScannedFiles" : 0,
      "numberOfSkippedFiles" : 0,
      "numberOfFilesForIndexing" : 0,
      "numberOfFilesFullyIndexedByInfrastructureExtensions" : 0,
      "scanningTime" : 0,
      "timeProcessingUpToDateFiles" : 0,
      "timeUpdatingContentLessIndexes" : 0,
      "timeIndexingWithoutContent" : 0
    }, {
      "providerName" : "com.intellij.javaee.ExternalResourcesRootsProvider@7cce72bf",
      "numberOfScannedFiles" : 0,
      "numberOfSkippedFiles" : 0,
      "numberOfFilesForIndexing" : 0,
      "numberOfFilesFullyIndexedByInfrastructureExtensions" : 0,
      "scanningTime" : 0,
      "timeProcessingUpToDateFiles" : 0,
      "timeUpdatingContentLessIndexes" : 0,
      "timeIndexingWithoutContent" : 0
    }, {
      "providerName" : "com.intellij.ide.scratch.ScratchesAndConsolesIndexSetContributor@7f1c12bd",
      "numberOfScannedFiles" : 0,
      "numberOfSkippedFiles" : 0,
      "numberOfFilesForIndexing" : 0,
      "numberOfFilesFullyIndexedByInfrastructureExtensions" : 0,
      "scanningTime" : 0,
      "timeProcessingUpToDateFiles" : 0,
      "timeUpdatingContentLessIndexes" : 0,
      "timeIndexingWithoutContent" : 0
    }, {
      "providerName" : "org.jetbrains.kotlin.idea.core.script.dependencies.KotlinScriptDependenciesIndexableSetContributor@3c5780d6",
      "numberOfScannedFiles" : 0,
      "numberOfSkippedFiles" : 0,
      "numberOfFilesForIndexing" : 0,
      "numberOfFilesFullyIndexedByInfrastructureExtensions" : 0,
      "scanningTime" : 0,
      "timeProcessingUpToDateFiles" : 0,
      "timeUpdatingContentLessIndexes" : 0,
      "timeIndexingWithoutContent" : 0
    } ],
    "fileProviderStatistics" : [ ]
  }
}